[{"NodeType":"Namespace","Name":"_r59qFM","InnerNodes":[{"NodeType":"Class","Name":"_NNSfqZ","InnerNodes":[{"NodeType":"Method","Name":"_VnvkGjY","InnerNodes":[]}]},{"NodeType":"Class","Name":"Eg9ZeQ8","InnerNodes":[{"NodeType":"Method","Name":"_Xqn3ee","InnerNodes":[]},{"NodeType":"Method","Name":"WpbfeOe","InnerNodes":[]},{"NodeType":"Method","Name":"_BiTKFjI","InnerNodes":[]},{"NodeType":"Method","Name":"_IfyRIof","InnerNodes":[]},{"NodeType":"Method","Name":"_SHKA3iI","InnerNodes":[]},{"NodeType":"Method","Name":"_MBIn72h","InnerNodes":[]},{"NodeType":"Method","Name":"bDZBXI","InnerNodes":[]},{"NodeType":"Method","Name":"XSH98Vi","InnerNodes":[]},{"NodeType":"Method","Name":"_ceNUM7","InnerNodes":[]}]},{"NodeType":"Class","Name":"IwiucCV","InnerNodes":[{"NodeType":"Method","Name":"ITryfJ7","InnerNodes":[]},{"NodeType":"Method","Name":"nEFyiX","InnerNodes":[]},{"NodeType":"Method","Name":"_Sc8KGW9","InnerNodes":[]},{"NodeType":"Method","Name":"HIXUUIs","InnerNodes":[]},{"NodeType":"Method","Name":"sQxNE6","InnerNodes":[]}]},{"NodeType":"Class","Name":"IDTIkWd","InnerNodes":[{"NodeType":"Method","Name":"_ZiE5D6I","InnerNodes":[]},{"NodeType":"Method","Name":"_snYMEF","InnerNodes":[]},{"NodeType":"Method","Name":"_QuYof9F","InnerNodes":[]},{"NodeType":"Method","Name":"BLfiAHI","InnerNodes":[]},{"NodeType":"Method","Name":"rt1KwL","InnerNodes":[]},{"NodeType":"Method","Name":"Kefx1my","InnerNodes":[]},{"NodeType":"Method","Name":"_FeJgoix","InnerNodes":[]},{"NodeType":"Method","Name":"_EHx8BU","InnerNodes":[]},{"NodeType":"Method","Name":"_d9E0eD","InnerNodes":[]}]},{"NodeType":"Class","Name":"EFOn8em","InnerNodes":[{"NodeType":"Method","Name":"BAGwzNI","InnerNodes":[]}]}]},{"NodeType":"Namespace","Name":"Sh2sIi5","InnerNodes":[{"NodeType":"Class","Name":"_RF6C2fU","InnerNodes":[{"NodeType":"Method","Name":"_YvLwO9y","InnerNodes":[]}]},{"NodeType":"Class","Name":"Sx9JsgZ","InnerNodes":[{"NodeType":"Method","Name":"FGi62z9","InnerNodes":[]},{"NodeType":"Method","Name":"_pVRAMG","InnerNodes":[]},{"NodeType":"Method","Name":"_I1u1DA","InnerNodes":[]},{"NodeType":"Method","Name":"_VyZ5RR","InnerNodes":[]},{"NodeType":"Method","Name":"_wdPBha","InnerNodes":[]},{"NodeType":"Method","Name":"_GIC7FaM","InnerNodes":[]},{"NodeType":"Method","Name":"_EF_K37","InnerNodes":[]},{"NodeType":"Method","Name":"IgXDdUA","InnerNodes":[]},{"NodeType":"Method","Name":"_KzFTWE2","InnerNodes":[]}]},{"NodeType":"Class","Name":"_UeO6irI","InnerNodes":[{"NodeType":"Method","Name":"wcuoDj","InnerNodes":[]},{"NodeType":"Method","Name":"_HoTaYxQ","InnerNodes":[]}]},{"NodeType":"Class","Name":"_LkL6ME","InnerNodes":[{"NodeType":"Method","Name":"_JeOcrs","InnerNodes":[]},{"NodeType":"Method","Name":"_SpejIOH","InnerNodes":[]},{"NodeType":"Method","Name":"_TvSip8D","InnerNodes":[]},{"NodeType":"Method","Name":"_TBsFxjc","InnerNodes":[]},{"NodeType":"Method","Name":"vKFSEW","InnerNodes":[]},{"NodeType":"Method","Name":"_n2Lpbm","InnerNodes":[]}]},{"NodeType":"Class","Name":"_pAiooE","InnerNodes":[{"NodeType":"Method","Name":"_ZKqISkF","InnerNodes":[]},{"NodeType":"Method","Name":"vs4edh","InnerNodes":[]},{"NodeType":"Method","Name":"_UgcNqEF","InnerNodes":[]},{"NodeType":"Method","Name":"KSiNIot","InnerNodes":[]},{"NodeType":"Method","Name":"cXNnRN","InnerNodes":[]}]},{"NodeType":"Class","Name":"_YUg267J","InnerNodes":[{"NodeType":"Method","Name":"_StIPmJ","InnerNodes":[]},{"NodeType":"Method","Name":"PdLywV","InnerNodes":[]},{"NodeType":"Method","Name":"AdpH6MF","InnerNodes":[]},{"NodeType":"Method","Name":"CP7uv8","InnerNodes":[]},{"NodeType":"Method","Name":"gxzksW","InnerNodes":[]},{"NodeType":"Method","Name":"Be6z8h","InnerNodes":[]}]},{"NodeType":"Class","Name":"_DtLBzO","InnerNodes":[{"NodeType":"Method","Name":"_GK35pOr","InnerNodes":[]},{"NodeType":"Method","Name":"Vzf2tX8","InnerNodes":[]},{"NodeType":"Method","Name":"_Jx26yHx","InnerNodes":[]}]},{"NodeType":"Class","Name":"_YWqbQo2","InnerNodes":[{"NodeType":"Method","Name":"uCnjse","InnerNodes":[]},{"NodeType":"Method","Name":"_Wxie9UF","InnerNodes":[]},{"NodeType":"Method","Name":"_M81b7K","InnerNodes":[]},{"NodeType":"Method","Name":"MbB8Geg","InnerNodes":[]},{"NodeType":"Method","Name":"_Dc_ILaY","InnerNodes":[]},{"NodeType":"Method","Name":"ZOzhiIo","InnerNodes":[]}]}]},{"NodeType":"Namespace","Name":"YBicWY","InnerNodes":[{"NodeType":"Class","Name":"_WIHDiPt","InnerNodes":[{"NodeType":"Method","Name":"Iubb283","InnerNodes":[]},{"NodeType":"Method","Name":"aOZ0gb","InnerNodes":[]},{"NodeType":"Method","Name":"bDYufS","InnerNodes":[]}]},{"NodeType":"Class","Name":"_pbEHpZ","InnerNodes":[{"NodeType":"Method","Name":"_IIgVQS","InnerNodes":[]}]},{"NodeType":"Class","Name":"EINEbq3","InnerNodes":[{"NodeType":"Method","Name":"_N1ORg7","InnerNodes":[]},{"NodeType":"Method","Name":"_fda4U4","InnerNodes":[]},{"NodeType":"Method","Name":"T9TyQP","InnerNodes":[]},{"NodeType":"Method","Name":"YJ3ajzd","InnerNodes":[]},{"NodeType":"Method","Name":"yOOM6z","InnerNodes":[]}]},{"NodeType":"Class","Name":"Ix_xCsX","InnerNodes":[{"NodeType":"Method","Name":"IJn4Rq7","InnerNodes":[]},{"NodeType":"Method","Name":"_aSxHOM","InnerNodes":[]},{"NodeType":"Method","Name":"szzDib","InnerNodes":[]},{"NodeType":"Method","Name":"_PfGt91n","InnerNodes":[]},{"NodeType":"Method","Name":"_wk_zZM","InnerNodes":[]},{"NodeType":"Method","Name":"_MFUszBv","InnerNodes":[]},{"NodeType":"Method","Name":"_MU9U_q","InnerNodes":[]}]},{"NodeType":"Class","Name":"_vh1mNI","InnerNodes":[{"NodeType":"Method","Name":"_yFQPVb","InnerNodes":[]},{"NodeType":"Method","Name":"TVExPL","InnerNodes":[]},{"NodeType":"Method","Name":"_TFV6gkF","InnerNodes":[]},{"NodeType":"Method","Name":"_AW32FO","InnerNodes":[]},{"NodeType":"Method","Name":"_DPI7RkZ","InnerNodes":[]},{"NodeType":"Method","Name":"SfxiN9v","InnerNodes":[]}]},{"NodeType":"Class","Name":"d2_4n0","InnerNodes":[{"NodeType":"Method","Name":"_S3sxEV","InnerNodes":[]},{"NodeType":"Method","Name":"FdPIdpi","InnerNodes":[]},{"NodeType":"Method","Name":"N8Dmu4","InnerNodes":[]},{"NodeType":"Method","Name":"_Qtoe5z","InnerNodes":[]},{"NodeType":"Method","Name":"UbxOG_","InnerNodes":[]},{"NodeType":"Method","Name":"_gmk59t","InnerNodes":[]},{"NodeType":"Method","Name":"KeGqnTg","InnerNodes":[]}]},{"NodeType":"Class","Name":"vPCU0F","InnerNodes":[{"NodeType":"Method","Name":"_YBiIVgF","InnerNodes":[]},{"NodeType":"Method","Name":"aK7GAk","InnerNodes":[]},{"NodeType":"Method","Name":"XZgYKjI","InnerNodes":[]},{"NodeType":"Method","Name":"_CJVTpu8","InnerNodes":[]}]},{"NodeType":"Class","Name":"Txod3Py","InnerNodes":[{"NodeType":"Method","Name":"_f5QCPJ","InnerNodes":[]},{"NodeType":"Method","Name":"_NkfZWUB","InnerNodes":[]},{"NodeType":"Method","Name":"_RIYhcUh","InnerNodes":[]},{"NodeType":"Method","Name":"FqdqhtV","InnerNodes":[]},{"NodeType":"Method","Name":"_djmXob","InnerNodes":[]},{"NodeType":"Method","Name":"_EtoHyS2","InnerNodes":[]},{"NodeType":"Method","Name":"GrJAB9K","InnerNodes":[]}]}]},{"NodeType":"Namespace","Name":"Wwak6d","InnerNodes":[{"NodeType":"Class","Name":"LP40hB2","InnerNodes":[{"NodeType":"Method","Name":"_YsyHeRC","InnerNodes":[]}]},{"NodeType":"Class","Name":"MIeWa8Y","InnerNodes":[{"NodeType":"Method","Name":"_L1yhJt","InnerNodes":[]},{"NodeType":"Method","Name":"_E7iIUk","InnerNodes":[]},{"NodeType":"Method","Name":"_PIyaUn","InnerNodes":[]},{"NodeType":"Method","Name":"_Pt7WkDy","InnerNodes":[]},{"NodeType":"Method","Name":"qIfONg","InnerNodes":[]}]},{"NodeType":"Class","Name":"VRyibOC","InnerNodes":[{"NodeType":"Method","Name":"YkIjXj","InnerNodes":[]},{"NodeType":"Method","Name":"ZWt8THj","InnerNodes":[]},{"NodeType":"Method","Name":"_Wwnp2T","InnerNodes":[]}]},{"NodeType":"Class","Name":"_xzebTB","InnerNodes":[{"NodeType":"Method","Name":"O0Qk1e","InnerNodes":[]},{"NodeType":"Method","Name":"_rB9iPH","InnerNodes":[]},{"NodeType":"Method","Name":"ADeoAw","InnerNodes":[]}]},{"NodeType":"Class","Name":"BRSNdqw","InnerNodes":[{"NodeType":"Method","Name":"DcCB2I","InnerNodes":[]},{"NodeType":"Method","Name":"_WFnXKCW","InnerNodes":[]},{"NodeType":"Method","Name":"N1yx2v","InnerNodes":[]},{"NodeType":"Method","Name":"_EiteCV","InnerNodes":[]},{"NodeType":"Method","Name":"UG7TLj","InnerNodes":[]}]},{"NodeType":"Class","Name":"_KPgCKEU","InnerNodes":[{"NodeType":"Method","Name":"_SrRUoea","InnerNodes":[]},{"NodeType":"Method","Name":"IHCiuMi","InnerNodes":[]},{"NodeType":"Method","Name":"_UPPCBtN","InnerNodes":[]}]}]},{"NodeType":"Namespace","Name":"_PgvAR5h","InnerNodes":[{"NodeType":"Class","Name":"_SA0Eimz","InnerNodes":[{"NodeType":"Method","Name":"_NDITMix","InnerNodes":[]}]},{"NodeType":"Class","Name":"LFJpXo","InnerNodes":[{"NodeType":"Method","Name":"iuKiLN","InnerNodes":[]},{"NodeType":"Method","Name":"_Yvia8Qd","InnerNodes":[]},{"NodeType":"Method","Name":"CbdJi1T","InnerNodes":[]},{"NodeType":"Method","Name":"_Vr2SwVo","InnerNodes":[]},{"NodeType":"Method","Name":"_G5AA7S","InnerNodes":[]},{"NodeType":"Method","Name":"_IcIabJ0","InnerNodes":[]},{"NodeType":"Method","Name":"_SH0ocS3","InnerNodes":[]},{"NodeType":"Method","Name":"VB5Tjph","InnerNodes":[]},{"NodeType":"Method","Name":"nNBmPJ","InnerNodes":[]}]},{"NodeType":"Class","Name":"_DIu0jpM","InnerNodes":[{"NodeType":"Method","Name":"Pi7hkqX","InnerNodes":[]},{"NodeType":"Method","Name":"WeLJyg","InnerNodes":[]}]},{"NodeType":"Class","Name":"NxqeEA","InnerNodes":[{"NodeType":"Method","Name":"QCsizx","InnerNodes":[]},{"NodeType":"Method","Name":"_NwC8xR9","InnerNodes":[]},{"NodeType":"Method","Name":"PMIuQm","InnerNodes":[]},{"NodeType":"Method","Name":"_KuayBwt","InnerNodes":[]},{"NodeType":"Method","Name":"BEU0YaD","InnerNodes":[]},{"NodeType":"Method","Name":"ISiyck","InnerNodes":[]}]},{"NodeType":"Class","Name":"HfK0Ww9","InnerNodes":[{"NodeType":"Method","Name":"_i1EN9I","InnerNodes":[]},{"NodeType":"Method","Name":"IIyaLL","InnerNodes":[]},{"NodeType":"Method","Name":"m_5VVh","InnerNodes":[]},{"NodeType":"Method","Name":"WiRe9Yv","InnerNodes":[]},{"NodeType":"Method","Name":"Mc9rLM","InnerNodes":[]}]},{"NodeType":"Class","Name":"_QfAEubA","InnerNodes":[{"NodeType":"Method","Name":"_JNnfR4x","InnerNodes":[]},{"NodeType":"Method","Name":"_Ci2KiZn","InnerNodes":[]},{"NodeType":"Method","Name":"QJFcJG6","InnerNodes":[]}]},{"NodeType":"Class","Name":"_VMBfPW4","InnerNodes":[{"NodeType":"Method","Name":"_kbqDT1","InnerNodes":[]},{"NodeType":"Method","Name":"kvtBxy","InnerNodes":[]},{"NodeType":"Method","Name":"_QinCbEU","InnerNodes":[]},{"NodeType":"Method","Name":"_It1A8F_","InnerNodes":[]},{"NodeType":"Method","Name":"C9djAR","InnerNodes":[]},{"NodeType":"Method","Name":"_KYqwTb","InnerNodes":[]},{"NodeType":"Method","Name":"_WKNoJEo","InnerNodes":[]},{"NodeType":"Method","Name":"_JtCKkh","InnerNodes":[]},{"NodeType":"Method","Name":"iCUTSB","InnerNodes":[]}]}]}]