[{"NodeType":"Namespace","Name":"hXiHQJ","InnerNodes":[{"NodeType":"Class","Name":"VYBFFx","InnerNodes":[{"NodeType":"Method","Name":"Gytejj","InnerNodes":[]},{"NodeType":"Method","Name":"z5SdvF","InnerNodes":[]},{"NodeType":"Method","Name":"_FGDeY3j","InnerNodes":[]},{"NodeType":"Method","Name":"_MKf0AVP","InnerNodes":[]},{"NodeType":"Method","Name":"_M3WSPM","InnerNodes":[]},{"NodeType":"Method","Name":"_drqICv","InnerNodes":[]},{"NodeType":"Method","Name":"MIqOdXL","InnerNodes":[]},{"NodeType":"Method","Name":"KNHVrj","InnerNodes":[]}]},{"NodeType":"Class","Name":"ML7gMI3","InnerNodes":[{"NodeType":"Method","Name":"_JwHhui3","InnerNodes":[]}]},{"NodeType":"Class","Name":"EbJqQ0A","InnerNodes":[{"NodeType":"Method","Name":"_j9nMoB","InnerNodes":[]},{"NodeType":"Method","Name":"_QgbkoyP","InnerNodes":[]},{"NodeType":"Method","Name":"_Iw2oHzS","InnerNodes":[]},{"NodeType":"Method","Name":"_NedBTv","InnerNodes":[]},{"NodeType":"Method","Name":"_ILSkpN","InnerNodes":[]}]},{"NodeType":"Class","Name":"_Q8OZ3k","InnerNodes":[{"NodeType":"Method","Name":"WUNMh6V","InnerNodes":[]},{"NodeType":"Method","Name":"_Scktfie","InnerNodes":[]},{"NodeType":"Method","Name":"NPXdyg4","InnerNodes":[]},{"NodeType":"Method","Name":"QpvjsQ","InnerNodes":[]},{"NodeType":"Method","Name":"wr9wSF","InnerNodes":[]},{"NodeType":"Method","Name":"_KD0UxVA","InnerNodes":[]},{"NodeType":"Method","Name":"mMIVCw","InnerNodes":[]},{"NodeType":"Method","Name":"QCJMZHk","InnerNodes":[]}]},{"NodeType":"Class","Name":"_WBdGKig","InnerNodes":[{"NodeType":"Method","Name":"NtGuKY","InnerNodes":[]},{"NodeType":"Method","Name":"_YrNmI1i","InnerNodes":[]},{"NodeType":"Method","Name":"_WA9r8A","InnerNodes":[]},{"NodeType":"Method","Name":"TiKYv80","InnerNodes":[]},{"NodeType":"Method","Name":"_dQkZsj","InnerNodes":[]},{"NodeType":"Method","Name":"_IacyfYJ","InnerNodes":[]},{"NodeType":"Method","Name":"Ir2V3mO","InnerNodes":[]},{"NodeType":"Method","Name":"DXXoC_","InnerNodes":[]}]}]},{"NodeType":"Namespace","Name":"zxee_2","InnerNodes":[{"NodeType":"Class","Name":"_EdEs_wY","InnerNodes":[{"NodeType":"Method","Name":"BWA3sKM","InnerNodes":[]},{"NodeType":"Method","Name":"_XTUuggg","InnerNodes":[]},{"NodeType":"Method","Name":"MjICxyk","InnerNodes":[]},{"NodeType":"Method","Name":"_DEpYaNF","InnerNodes":[]},{"NodeType":"Method","Name":"oSTspy","InnerNodes":[]},{"NodeType":"Method","Name":"_CratVVs","InnerNodes":[]},{"NodeType":"Method","Name":"KDkDzpw","InnerNodes":[]}]},{"NodeType":"Class","Name":"Iis0hz","InnerNodes":[{"NodeType":"Method","Name":"_vip2Id","InnerNodes":[]}]},{"NodeType":"Class","Name":"CQtgg4W","InnerNodes":[{"NodeType":"Method","Name":"JdUoU7","InnerNodes":[]},{"NodeType":"Method","Name":"_Qa37Js","InnerNodes":[]},{"NodeType":"Method","Name":"_ZxngDPi","InnerNodes":[]},{"NodeType":"Method","Name":"fo3tPp","InnerNodes":[]},{"NodeType":"Method","Name":"DiRicO2","InnerNodes":[]},{"NodeType":"Method","Name":"_i2pFKs","InnerNodes":[]},{"NodeType":"Method","Name":"BtFvot","InnerNodes":[]}]},{"NodeType":"Class","Name":"_gO63Wv","InnerNodes":[{"NodeType":"Method","Name":"NdHyPM","InnerNodes":[]},{"NodeType":"Method","Name":"Na58RvI","InnerNodes":[]},{"NodeType":"Method","Name":"_OoSB5RH","InnerNodes":[]},{"NodeType":"Method","Name":"IDkn2IS","InnerNodes":[]},{"NodeType":"Method","Name":"_r0TpRB","InnerNodes":[]},{"NodeType":"Method","Name":"uIUMbc","InnerNodes":[]},{"NodeType":"Method","Name":"_aI5idU","InnerNodes":[]},{"NodeType":"Method","Name":"_dMxuVq","InnerNodes":[]},{"NodeType":"Method","Name":"_e65k4t","InnerNodes":[]}]},{"NodeType":"Class","Name":"_hjmMHw","InnerNodes":[{"NodeType":"Method","Name":"sSAKdv","InnerNodes":[]},{"NodeType":"Method","Name":"_QPkQyw7","InnerNodes":[]}]},{"NodeType":"Class","Name":"IvkqyDO","InnerNodes":[{"NodeType":"Method","Name":"_HamjTp3","InnerNodes":[]},{"NodeType":"Method","Name":"IrWgKb3","InnerNodes":[]},{"NodeType":"Method","Name":"NPN4eKG","InnerNodes":[]},{"NodeType":"Method","Name":"E_Zeuq","InnerNodes":[]},{"NodeType":"Method","Name":"iAQ1q6","InnerNodes":[]},{"NodeType":"Method","Name":"mo4ia5","InnerNodes":[]}]},{"NodeType":"Class","Name":"SsVjSiM","InnerNodes":[{"NodeType":"Method","Name":"hOB2gS","InnerNodes":[]},{"NodeType":"Method","Name":"_reLA0A","InnerNodes":[]},{"NodeType":"Method","Name":"_RMcSZw","InnerNodes":[]},{"NodeType":"Method","Name":"_bjwKw3","InnerNodes":[]},{"NodeType":"Method","Name":"_VSzOy6_","InnerNodes":[]},{"NodeType":"Method","Name":"Ticau5","InnerNodes":[]},{"NodeType":"Method","Name":"NUDjstE","InnerNodes":[]}]}]},{"NodeType":"Namespace","Name":"_aeq1UL","InnerNodes":[{"NodeType":"Class","Name":"HuKLqFr","InnerNodes":[{"NodeType":"Method","Name":"PFckTsz","InnerNodes":[]},{"NodeType":"Method","Name":"RzMYYdY","InnerNodes":[]},{"NodeType":"Method","Name":"_fJ7HWE","InnerNodes":[]},{"NodeType":"Method","Name":"DyAFDU","InnerNodes":[]},{"NodeType":"Method","Name":"Cmkzfoi","InnerNodes":[]},{"NodeType":"Method","Name":"_ZvN69u5","InnerNodes":[]},{"NodeType":"Method","Name":"NGS1iMi","InnerNodes":[]},{"NodeType":"Method","Name":"_UTHcxR8","InnerNodes":[]},{"NodeType":"Method","Name":"YOp4tH1","InnerNodes":[]}]},{"NodeType":"Class","Name":"tIxZYW","InnerNodes":[{"NodeType":"Method","Name":"sv8_SO","InnerNodes":[]},{"NodeType":"Method","Name":"_nQbH1X","InnerNodes":[]},{"NodeType":"Method","Name":"_STiSnPJ","InnerNodes":[]},{"NodeType":"Method","Name":"_Af1BLxS","InnerNodes":[]},{"NodeType":"Method","Name":"QMg94mI","InnerNodes":[]},{"NodeType":"Method","Name":"_Oyoimf","InnerNodes":[]},{"NodeType":"Method","Name":"TcPbkbS","InnerNodes":[]},{"NodeType":"Method","Name":"M4dh7B","InnerNodes":[]}]},{"NodeType":"Class","Name":"_WeU_kNW","InnerNodes":[{"NodeType":"Method","Name":"PpIVJzK","InnerNodes":[]},{"NodeType":"Method","Name":"dfRiw7","InnerNodes":[]},{"NodeType":"Method","Name":"YVAFyt","InnerNodes":[]},{"NodeType":"Method","Name":"wkEI60","InnerNodes":[]},{"NodeType":"Method","Name":"ZPNC9b","InnerNodes":[]},{"NodeType":"Method","Name":"i6I7Uv","InnerNodes":[]},{"NodeType":"Method","Name":"_DvDfct_","InnerNodes":[]}]},{"NodeType":"Class","Name":"_dzYoBI","InnerNodes":[{"NodeType":"Method","Name":"_gOLSnJ","InnerNodes":[]},{"NodeType":"Method","Name":"mqugBW","InnerNodes":[]},{"NodeType":"Method","Name":"_Msfbg6V","InnerNodes":[]},{"NodeType":"Method","Name":"KUA3sS","InnerNodes":[]},{"NodeType":"Method","Name":"_Sm9XM5v","InnerNodes":[]}]},{"NodeType":"Class","Name":"_WUBzLWz","InnerNodes":[{"NodeType":"Method","Name":"_wEE4ZE","InnerNodes":[]},{"NodeType":"Method","Name":"GcSYW69","InnerNodes":[]},{"NodeType":"Method","Name":"p_wKIK","InnerNodes":[]},{"NodeType":"Method","Name":"ZN8wHUa","InnerNodes":[]},{"NodeType":"Method","Name":"D9IpIM","InnerNodes":[]},{"NodeType":"Method","Name":"_WJY3zwi","InnerNodes":[]}]},{"NodeType":"Class","Name":"Awdm7e","InnerNodes":[{"NodeType":"Method","Name":"LfWXkK8","InnerNodes":[]},{"NodeType":"Method","Name":"_vII928","InnerNodes":[]},{"NodeType":"Method","Name":"EIXUjLR","InnerNodes":[]},{"NodeType":"Method","Name":"_Fa1J__Z","InnerNodes":[]},{"NodeType":"Method","Name":"_IAZx9aY","InnerNodes":[]},{"NodeType":"Method","Name":"WXuEbTT","InnerNodes":[]}]}]},{"NodeType":"Namespace","Name":"_ArDPHgJ","InnerNodes":[{"NodeType":"Class","Name":"_Xi3NKmI","InnerNodes":[{"NodeType":"Method","Name":"IiVgVX2","InnerNodes":[]},{"NodeType":"Method","Name":"_i2e1vu","InnerNodes":[]},{"NodeType":"Method","Name":"_IUeRZwt","InnerNodes":[]},{"NodeType":"Method","Name":"_UiNAJqp","InnerNodes":[]},{"NodeType":"Method","Name":"_vRh2wd","InnerNodes":[]},{"NodeType":"Method","Name":"RO9LKS_","InnerNodes":[]},{"NodeType":"Method","Name":"_uSZAfV","InnerNodes":[]}]},{"NodeType":"Class","Name":"Cd926We","InnerNodes":[{"NodeType":"Method","Name":"MjBddnE","InnerNodes":[]},{"NodeType":"Method","Name":"IA478u","InnerNodes":[]},{"NodeType":"Method","Name":"JIhN_0U","InnerNodes":[]}]},{"NodeType":"Class","Name":"LQKyY1","InnerNodes":[{"NodeType":"Method","Name":"mCvhgs","InnerNodes":[]},{"NodeType":"Method","Name":"_KBz7S2G","InnerNodes":[]},{"NodeType":"Method","Name":"d0q938","InnerNodes":[]},{"NodeType":"Method","Name":"jDZRum","InnerNodes":[]},{"NodeType":"Method","Name":"_PyitFnT","InnerNodes":[]}]},{"NodeType":"Class","Name":"SRmTIk","InnerNodes":[{"NodeType":"Method","Name":"_OmUGIb","InnerNodes":[]}]},{"NodeType":"Class","Name":"LY9uUbE","InnerNodes":[{"NodeType":"Method","Name":"WQc6V7k","InnerNodes":[]},{"NodeType":"Method","Name":"ImDAKb","InnerNodes":[]},{"NodeType":"Method","Name":"_IogeZP_","InnerNodes":[]},{"NodeType":"Method","Name":"FMBxq3r","InnerNodes":[]},{"NodeType":"Method","Name":"_z8QzaA","InnerNodes":[]},{"NodeType":"Method","Name":"_PcaZwgy","InnerNodes":[]},{"NodeType":"Method","Name":"_MyHIyuh","InnerNodes":[]}]},{"NodeType":"Class","Name":"_aGvuI9","InnerNodes":[{"NodeType":"Method","Name":"_HuIyMR","InnerNodes":[]},{"NodeType":"Method","Name":"UiM_Ssm","InnerNodes":[]},{"NodeType":"Method","Name":"txnOsp","InnerNodes":[]},{"NodeType":"Method","Name":"r9gDNY","InnerNodes":[]},{"NodeType":"Method","Name":"RfET9_j","InnerNodes":[]},{"NodeType":"Method","Name":"_KtKeK9J","InnerNodes":[]},{"NodeType":"Method","Name":"_ELgNsfY","InnerNodes":[]}]}]},{"NodeType":"Namespace","Name":"pof1Cc","InnerNodes":[{"NodeType":"Class","Name":"VF74Fgr","InnerNodes":[{"NodeType":"Method","Name":"_qIvvxr","InnerNodes":[]},{"NodeType":"Method","Name":"_IIKmEDq","InnerNodes":[]},{"NodeType":"Method","Name":"_OfqHek","InnerNodes":[]},{"NodeType":"Method","Name":"_XUNri2m","InnerNodes":[]},{"NodeType":"Method","Name":"_TGzjis7","InnerNodes":[]}]},{"NodeType":"Class","Name":"_TZy_tiF","InnerNodes":[{"NodeType":"Method","Name":"gJtZxQ","InnerNodes":[]},{"NodeType":"Method","Name":"_KspIr5","InnerNodes":[]},{"NodeType":"Method","Name":"KiGXmKE","InnerNodes":[]}]},{"NodeType":"Class","Name":"QeiTzC","InnerNodes":[{"NodeType":"Method","Name":"qu2pIr","InnerNodes":[]},{"NodeType":"Method","Name":"UcsgGaK","InnerNodes":[]},{"NodeType":"Method","Name":"_YI3NrUg","InnerNodes":[]},{"NodeType":"Method","Name":"_Qnk15v","InnerNodes":[]},{"NodeType":"Method","Name":"MSgYGw6","InnerNodes":[]},{"NodeType":"Method","Name":"KQDMrXQ","InnerNodes":[]},{"NodeType":"Method","Name":"MIur4W","InnerNodes":[]},{"NodeType":"Method","Name":"YdJryTq","InnerNodes":[]},{"NodeType":"Method","Name":"mhCfTV","InnerNodes":[]}]},{"NodeType":"Class","Name":"_ZeZ1Jr","InnerNodes":[{"NodeType":"Method","Name":"VC5dTiD","InnerNodes":[]}]},{"NodeType":"Class","Name":"_Xr8Z7A","InnerNodes":[{"NodeType":"Method","Name":"_WkVQfg","InnerNodes":[]},{"NodeType":"Method","Name":"_U8kxmU","InnerNodes":[]},{"NodeType":"Method","Name":"Ru9zY3i","InnerNodes":[]}]},{"NodeType":"Class","Name":"_StBato","InnerNodes":[{"NodeType":"Method","Name":"_PBmAUAw","InnerNodes":[]},{"NodeType":"Method","Name":"_njfqcQ","InnerNodes":[]},{"NodeType":"Method","Name":"Akhe1cF","InnerNodes":[]},{"NodeType":"Method","Name":"_p9yDti","InnerNodes":[]},{"NodeType":"Method","Name":"_LQM2Tp4","InnerNodes":[]}]}]},{"NodeType":"Namespace","Name":"BnDsgrx","InnerNodes":[{"NodeType":"Class","Name":"OiJISX","InnerNodes":[{"NodeType":"Method","Name":"_UIRUJkd","InnerNodes":[]},{"NodeType":"Method","Name":"QiyzfOn","InnerNodes":[]},{"NodeType":"Method","Name":"_Tq1yZ99","InnerNodes":[]}]},{"NodeType":"Class","Name":"ZfIy_6u","InnerNodes":[{"NodeType":"Method","Name":"ZxYyCUO","InnerNodes":[]},{"NodeType":"Method","Name":"_rI7uGv","InnerNodes":[]},{"NodeType":"Method","Name":"MjTN88a","InnerNodes":[]},{"NodeType":"Method","Name":"SdcvDpE","InnerNodes":[]},{"NodeType":"Method","Name":"NvsHzDM","InnerNodes":[]},{"NodeType":"Method","Name":"_OMR1e4M","InnerNodes":[]},{"NodeType":"Method","Name":"sw4YZq","InnerNodes":[]},{"NodeType":"Method","Name":"bbVk5k","InnerNodes":[]}]},{"NodeType":"Class","Name":"DXOR02S","InnerNodes":[{"NodeType":"Method","Name":"_HjU_jsf","InnerNodes":[]},{"NodeType":"Method","Name":"VD5rGh","InnerNodes":[]},{"NodeType":"Method","Name":"QIoRzZ","InnerNodes":[]},{"NodeType":"Method","Name":"cWHMPN","InnerNodes":[]},{"NodeType":"Method","Name":"_Ef089Y","InnerNodes":[]},{"NodeType":"Method","Name":"jrOHaI","InnerNodes":[]},{"NodeType":"Method","Name":"_nf4Hdh","InnerNodes":[]}]},{"NodeType":"Class","Name":"FDBNYva","InnerNodes":[{"NodeType":"Method","Name":"IkMLSV","InnerNodes":[]},{"NodeType":"Method","Name":"_i4GwNc","InnerNodes":[]},{"NodeType":"Method","Name":"_MsHZhMv","InnerNodes":[]},{"NodeType":"Method","Name":"_jIeMB_","InnerNodes":[]},{"NodeType":"Method","Name":"_DvitVYJ","InnerNodes":[]},{"NodeType":"Method","Name":"fSWTfC","InnerNodes":[]}]},{"NodeType":"Class","Name":"fakCJV","InnerNodes":[{"NodeType":"Method","Name":"d4dYcI","InnerNodes":[]},{"NodeType":"Method","Name":"uVbUE_","InnerNodes":[]},{"NodeType":"Method","Name":"_HFyM6Mz","InnerNodes":[]}]},{"NodeType":"Class","Name":"_NtI0mDE","InnerNodes":[{"NodeType":"Method","Name":"_ZrC55X9","InnerNodes":[]},{"NodeType":"Method","Name":"_AFw4ffI","InnerNodes":[]}]},{"NodeType":"Class","Name":"RRsehcP","InnerNodes":[{"NodeType":"Method","Name":"MI35WMX","InnerNodes":[]}]},{"NodeType":"Class","Name":"_eWhW12","InnerNodes":[{"NodeType":"Method","Name":"_ZggGDC","InnerNodes":[]},{"NodeType":"Method","Name":"u8L3sA","InnerNodes":[]},{"NodeType":"Method","Name":"UHvhmnQ","InnerNodes":[]},{"NodeType":"Method","Name":"Pqh9Nv","InnerNodes":[]},{"NodeType":"Method","Name":"vyi7Zy","InnerNodes":[]},{"NodeType":"Method","Name":"_CCdv7u","InnerNodes":[]},{"NodeType":"Method","Name":"SM5PzsF","InnerNodes":[]},{"NodeType":"Method","Name":"_OBEK8PX","InnerNodes":[]}]}]},{"NodeType":"Namespace","Name":"_IAhaIiB","InnerNodes":[{"NodeType":"Class","Name":"WbYL2y","InnerNodes":[{"NodeType":"Method","Name":"_gHCUDT","InnerNodes":[]},{"NodeType":"Method","Name":"_YIsv2XV","InnerNodes":[]},{"NodeType":"Method","Name":"_NmIE265","InnerNodes":[]}]},{"NodeType":"Class","Name":"QUdBE8","InnerNodes":[{"NodeType":"Method","Name":"_k7YAID","InnerNodes":[]},{"NodeType":"Method","Name":"_LvyYse","InnerNodes":[]}]}]},{"NodeType":"Namespace","Name":"_Twic1Cz","InnerNodes":[{"NodeType":"Class","Name":"BUAPakC","InnerNodes":[{"NodeType":"Method","Name":"_N4jUIW","InnerNodes":[]},{"NodeType":"Method","Name":"HQypx9O","InnerNodes":[]},{"NodeType":"Method","Name":"Kw7qPMO","InnerNodes":[]},{"NodeType":"Method","Name":"_UseFTQ","InnerNodes":[]},{"NodeType":"Method","Name":"BCYqgE","InnerNodes":[]},{"NodeType":"Method","Name":"_E2Ebfj","InnerNodes":[]}]},{"NodeType":"Class","Name":"_GoLdAi","InnerNodes":[{"NodeType":"Method","Name":"_DUrEpS","InnerNodes":[]},{"NodeType":"Method","Name":"QcbfYfY","InnerNodes":[]},{"NodeType":"Method","Name":"_Rw6cI8","InnerNodes":[]},{"NodeType":"Method","Name":"_BriI2SC","InnerNodes":[]},{"NodeType":"Method","Name":"_ybatus","InnerNodes":[]},{"NodeType":"Method","Name":"TxgTiz","InnerNodes":[]}]}]},{"NodeType":"Namespace","Name":"_zI7I37","InnerNodes":[{"NodeType":"Class","Name":"_Kcv30xy","InnerNodes":[{"NodeType":"Method","Name":"_P22IVa","InnerNodes":[]}]},{"NodeType":"Class","Name":"_mSouN0","InnerNodes":[{"NodeType":"Method","Name":"wmsmVy","InnerNodes":[]},{"NodeType":"Method","Name":"_CYu9xVK","InnerNodes":[]}]},{"NodeType":"Class","Name":"b44E8a","InnerNodes":[{"NodeType":"Method","Name":"RpvncAZ","InnerNodes":[]},{"NodeType":"Method","Name":"GkkbZpU","InnerNodes":[]},{"NodeType":"Method","Name":"Xvfp8O","InnerNodes":[]},{"NodeType":"Method","Name":"_iCXNSn","InnerNodes":[]},{"NodeType":"Method","Name":"IIiVWwM","InnerNodes":[]}]},{"NodeType":"Class","Name":"_DLb8bt","InnerNodes":[{"NodeType":"Method","Name":"PIPBjsm","InnerNodes":[]},{"NodeType":"Method","Name":"_prEq5o","InnerNodes":[]},{"NodeType":"Method","Name":"_nYIoKm","InnerNodes":[]},{"NodeType":"Method","Name":"_IieOtA","InnerNodes":[]},{"NodeType":"Method","Name":"ficyG9","InnerNodes":[]},{"NodeType":"Method","Name":"VeNtyG","InnerNodes":[]},{"NodeType":"Method","Name":"_xBw5Qu","InnerNodes":[]},{"NodeType":"Method","Name":"_Z_SSTc","InnerNodes":[]},{"NodeType":"Method","Name":"_VboIJ69","InnerNodes":[]}]}]}]