[{"NodeType":"Namespace","Name":"U9nCnk","InnerNodes":[{"NodeType":"Class","Name":"YSRPTp","InnerNodes":[{"NodeType":"Method","Name":"_XAPNo5","InnerNodes":[]},{"NodeType":"Method","Name":"QIzcIdI","InnerNodes":[]},{"NodeType":"Method","Name":"DMvDJZj","InnerNodes":[]},{"NodeType":"Method","Name":"NTbKiv","InnerNodes":[]},{"NodeType":"Method","Name":"Yzp4msi","InnerNodes":[]},{"NodeType":"Method","Name":"_snuVqZ","InnerNodes":[]},{"NodeType":"Method","Name":"Zd__TQk","InnerNodes":[]},{"NodeType":"Method","Name":"UGqT5h2","InnerNodes":[]},{"NodeType":"Method","Name":"HavDCiy","InnerNodes":[]}]}]},{"NodeType":"Namespace","Name":"JpqUYiA","InnerNodes":[{"NodeType":"Class","Name":"TIMCi0W","InnerNodes":[{"NodeType":"Method","Name":"GOAWdF","InnerNodes":[]},{"NodeType":"Method","Name":"_MHAAb8E","InnerNodes":[]},{"NodeType":"Method","Name":"_e0tdmh","InnerNodes":[]},{"NodeType":"Method","Name":"_PewgDmI","InnerNodes":[]},{"NodeType":"Method","Name":"_SDu1XO","InnerNodes":[]},{"NodeType":"Method","Name":"IkQoIj8","InnerNodes":[]},{"NodeType":"Method","Name":"srTJdI","InnerNodes":[]}]},{"NodeType":"Class","Name":"Rk3QGvz","InnerNodes":[{"NodeType":"Method","Name":"_ZsjrWj","InnerNodes":[]},{"NodeType":"Method","Name":"Q98Z3q","InnerNodes":[]},{"NodeType":"Method","Name":"RgpyV5","InnerNodes":[]},{"NodeType":"Method","Name":"RpRTafS","InnerNodes":[]}]},{"NodeType":"Class","Name":"_SoqtCv","InnerNodes":[{"NodeType":"Method","Name":"_Mezd22H","InnerNodes":[]},{"NodeType":"Method","Name":"RLtcy00","InnerNodes":[]},{"NodeType":"Method","Name":"_TiZ63dd","InnerNodes":[]},{"NodeType":"Method","Name":"_QxiNpFW","InnerNodes":[]},{"NodeType":"Method","Name":"_AY6mQen","InnerNodes":[]},{"NodeType":"Method","Name":"_YRVNet","InnerNodes":[]},{"NodeType":"Method","Name":"w0zomY","InnerNodes":[]}]},{"NodeType":"Class","Name":"_cDEpRI","InnerNodes":[{"NodeType":"Method","Name":"_AHyIgz","InnerNodes":[]},{"NodeType":"Method","Name":"_PCfOutB","InnerNodes":[]}]},{"NodeType":"Class","Name":"_KEs2Vp","InnerNodes":[{"NodeType":"Method","Name":"ZItzPc","InnerNodes":[]},{"NodeType":"Method","Name":"uvm6iz","InnerNodes":[]}]},{"NodeType":"Class","Name":"COzVS4I","InnerNodes":[{"NodeType":"Method","Name":"_Xr5Lc73","InnerNodes":[]},{"NodeType":"Method","Name":"HC_Zgss","InnerNodes":[]},{"NodeType":"Method","Name":"_zEBoNw","InnerNodes":[]},{"NodeType":"Method","Name":"AXcFfW7","InnerNodes":[]},{"NodeType":"Method","Name":"fBjRfV","InnerNodes":[]}]},{"NodeType":"Class","Name":"kVEEs0","InnerNodes":[{"NodeType":"Method","Name":"OHh0GV","InnerNodes":[]},{"NodeType":"Method","Name":"fONs6K","InnerNodes":[]},{"NodeType":"Method","Name":"VL3DsIP","InnerNodes":[]},{"NodeType":"Method","Name":"_QMYBYF","InnerNodes":[]},{"NodeType":"Method","Name":"_VQwZQt","InnerNodes":[]}]}]},{"NodeType":"Namespace","Name":"_IwBG_BV","InnerNodes":[{"NodeType":"Class","Name":"_KhMyiIB","InnerNodes":[{"NodeType":"Method","Name":"BS2fnH","InnerNodes":[]},{"NodeType":"Method","Name":"_LAmdLC","InnerNodes":[]},{"NodeType":"Method","Name":"_FKmvqVd","InnerNodes":[]},{"NodeType":"Method","Name":"_e2iKzP","InnerNodes":[]},{"NodeType":"Method","Name":"M_IzoX","InnerNodes":[]},{"NodeType":"Method","Name":"Riq8Oh","InnerNodes":[]},{"NodeType":"Method","Name":"_XubTcI","InnerNodes":[]},{"NodeType":"Method","Name":"_Kzw3oJ3","InnerNodes":[]}]},{"NodeType":"Class","Name":"BMI4JJi","InnerNodes":[{"NodeType":"Method","Name":"_ZEyeooe","InnerNodes":[]},{"NodeType":"Method","Name":"RVNICB6","InnerNodes":[]}]},{"NodeType":"Class","Name":"FC2qc7Q","InnerNodes":[{"NodeType":"Method","Name":"_Nf6yxw9","InnerNodes":[]},{"NodeType":"Method","Name":"BUtOPK","InnerNodes":[]},{"NodeType":"Method","Name":"_AiBPYa5","InnerNodes":[]},{"NodeType":"Method","Name":"LaOLWr","InnerNodes":[]},{"NodeType":"Method","Name":"OeTIfG","InnerNodes":[]},{"NodeType":"Method","Name":"_F5x5oR","InnerNodes":[]}]},{"NodeType":"Class","Name":"JroI43I","InnerNodes":[{"NodeType":"Method","Name":"FGQb_Vm","InnerNodes":[]}]},{"NodeType":"Class","Name":"_Eih5VJ","InnerNodes":[{"NodeType":"Method","Name":"_As2mhiU","InnerNodes":[]},{"NodeType":"Method","Name":"VfHIjAR","InnerNodes":[]},{"NodeType":"Method","Name":"Igx5ZB","InnerNodes":[]},{"NodeType":"Method","Name":"UNCZCkT","InnerNodes":[]},{"NodeType":"Method","Name":"_NSw5yI","InnerNodes":[]},{"NodeType":"Method","Name":"ipy3mV","InnerNodes":[]},{"NodeType":"Method","Name":"WOjPBuS","InnerNodes":[]},{"NodeType":"Method","Name":"I93B3q","InnerNodes":[]}]},{"NodeType":"Class","Name":"ILwjIEI","InnerNodes":[{"NodeType":"Method","Name":"EnUxAXr","InnerNodes":[]},{"NodeType":"Method","Name":"_hJAFRK","InnerNodes":[]},{"NodeType":"Method","Name":"_MVuqbc","InnerNodes":[]},{"NodeType":"Method","Name":"_KPnSVtG","InnerNodes":[]},{"NodeType":"Method","Name":"_E7VocS","InnerNodes":[]},{"NodeType":"Method","Name":"_DUwjYF","InnerNodes":[]},{"NodeType":"Method","Name":"_OBFNxwq","InnerNodes":[]}]},{"NodeType":"Class","Name":"Im21Wnr","InnerNodes":[{"NodeType":"Method","Name":"UcLpbn","InnerNodes":[]}]},{"NodeType":"Class","Name":"_MuMBsfy","InnerNodes":[{"NodeType":"Method","Name":"cXHb3Q","InnerNodes":[]},{"NodeType":"Method","Name":"Pp3GqF5","InnerNodes":[]},{"NodeType":"Method","Name":"IWGGA8b","InnerNodes":[]},{"NodeType":"Method","Name":"d344GR","InnerNodes":[]},{"NodeType":"Method","Name":"_qxjqem","InnerNodes":[]}]}]},{"NodeType":"Namespace","Name":"_MZs02D","InnerNodes":[{"NodeType":"Class","Name":"PE6WuRM","InnerNodes":[{"NodeType":"Method","Name":"_CHvGnQ","InnerNodes":[]},{"NodeType":"Method","Name":"_vaEIur","InnerNodes":[]},{"NodeType":"Method","Name":"fbbQud","InnerNodes":[]},{"NodeType":"Method","Name":"Hu68BfI","InnerNodes":[]},{"NodeType":"Method","Name":"_BP94Byf","InnerNodes":[]},{"NodeType":"Method","Name":"_CSmnLeI","InnerNodes":[]}]},{"NodeType":"Class","Name":"_HHmNJT","InnerNodes":[{"NodeType":"Method","Name":"NOIa9wB","InnerNodes":[]},{"NodeType":"Method","Name":"LfofrS","InnerNodes":[]},{"NodeType":"Method","Name":"_OFZEHiH","InnerNodes":[]},{"NodeType":"Method","Name":"w3vR1D","InnerNodes":[]},{"NodeType":"Method","Name":"yDsHi0","InnerNodes":[]}]}]}]