[{"NodeType":"Namespace","Name":"gLhLzH","InnerNodes":[{"NodeType":"Class","Name":"_Uycx5YW","InnerNodes":[{"NodeType":"Method","Name":"ARFGX8i","InnerNodes":[]},{"NodeType":"Method","Name":"gPabpq","InnerNodes":[]}]}]},{"NodeType":"Namespace","Name":"_Iyhn58","InnerNodes":[{"NodeType":"Class","Name":"_MIhJWr","InnerNodes":[{"NodeType":"Method","Name":"_MUXHOs_","InnerNodes":[]},{"NodeType":"Method","Name":"occ2cR","InnerNodes":[]},{"NodeType":"Method","Name":"_CQXIg6","InnerNodes":[]},{"NodeType":"Method","Name":"PHYUm2","InnerNodes":[]},{"NodeType":"Method","Name":"_SofYry","InnerNodes":[]},{"NodeType":"Method","Name":"_NH3FyT","InnerNodes":[]}]},{"NodeType":"Class","Name":"_VfwA60","InnerNodes":[{"NodeType":"Method","Name":"wMsCHu","InnerNodes":[]},{"NodeType":"Method","Name":"_Zi6r83M","InnerNodes":[]}]},{"NodeType":"Class","Name":"NQtXFD","InnerNodes":[{"NodeType":"Method","Name":"GG2y6Nz","InnerNodes":[]},{"NodeType":"Method","Name":"B4BoDF","InnerNodes":[]},{"NodeType":"Method","Name":"V7vqP0","InnerNodes":[]},{"NodeType":"Method","Name":"Uo_P69E","InnerNodes":[]}]},{"NodeType":"Class","Name":"LjegIz","InnerNodes":[{"NodeType":"Method","Name":"Kko6uO","InnerNodes":[]},{"NodeType":"Method","Name":"_Iud0qCt","InnerNodes":[]},{"NodeType":"Method","Name":"_XkdC_J","InnerNodes":[]},{"NodeType":"Method","Name":"wkEt69","InnerNodes":[]},{"NodeType":"Method","Name":"AZS6ik","InnerNodes":[]}]},{"NodeType":"Class","Name":"JsqN7Ld","InnerNodes":[{"NodeType":"Method","Name":"QL7V510","InnerNodes":[]},{"NodeType":"Method","Name":"JWTIQ_Z","InnerNodes":[]},{"NodeType":"Method","Name":"_fc2j7I","InnerNodes":[]},{"NodeType":"Method","Name":"_RqBgqC","InnerNodes":[]}]},{"NodeType":"Class","Name":"Xe5saT_","InnerNodes":[{"NodeType":"Method","Name":"_KiJjQFP","InnerNodes":[]},{"NodeType":"Method","Name":"_YxJY0_e","InnerNodes":[]},{"NodeType":"Method","Name":"OCGJFJ","InnerNodes":[]},{"NodeType":"Method","Name":"_TMGithy","InnerNodes":[]}]},{"NodeType":"Class","Name":"_pu2XIX","InnerNodes":[{"NodeType":"Method","Name":"_Oiw0yOG","InnerNodes":[]},{"NodeType":"Method","Name":"ORKko2q","InnerNodes":[]},{"NodeType":"Method","Name":"_JFHwUqg","InnerNodes":[]},{"NodeType":"Method","Name":"_sYhS_C","InnerNodes":[]},{"NodeType":"Method","Name":"_fdcKQw","InnerNodes":[]},{"NodeType":"Method","Name":"fLQzEf","InnerNodes":[]},{"NodeType":"Method","Name":"_UubeqWI","InnerNodes":[]},{"NodeType":"Method","Name":"DOLvi1x","InnerNodes":[]},{"NodeType":"Method","Name":"LmNR94K","InnerNodes":[]}]}]}]