[{"NodeType":"Namespace","Name":"HE8hA0b","InnerNodes":[{"NodeType":"Class","Name":"_Ex4Hjc","InnerNodes":[{"NodeType":"Method","Name":"HEb2U7","InnerNodes":[]},{"NodeType":"Method","Name":"_RnbPpFU","InnerNodes":[]},{"NodeType":"Method","Name":"_Qat6rku","InnerNodes":[]},{"NodeType":"Method","Name":"uV_TDY","InnerNodes":[]},{"NodeType":"Method","Name":"iHWA7K","InnerNodes":[]}]}]},{"NodeType":"Namespace","Name":"_X0giia","InnerNodes":[{"NodeType":"Class","Name":"QAs69p","InnerNodes":[{"NodeType":"Method","Name":"_pWXRm8","InnerNodes":[]},{"NodeType":"Method","Name":"Hdp3VY","InnerNodes":[]},{"NodeType":"Method","Name":"_rohyve","InnerNodes":[]},{"NodeType":"Method","Name":"FJrZyFt","InnerNodes":[]},{"NodeType":"Method","Name":"_fwZnia","InnerNodes":[]}]},{"NodeType":"Class","Name":"_BjXKMy","InnerNodes":[{"NodeType":"Method","Name":"_jBtjnp","InnerNodes":[]},{"NodeType":"Method","Name":"_ft13oj","InnerNodes":[]},{"NodeType":"Method","Name":"ItTzij","InnerNodes":[]},{"NodeType":"Method","Name":"Gq41nw1","InnerNodes":[]},{"NodeType":"Method","Name":"_dhAYei","InnerNodes":[]},{"NodeType":"Method","Name":"_DC9hrID","InnerNodes":[]},{"NodeType":"Method","Name":"_hpsIYg","InnerNodes":[]}]},{"NodeType":"Class","Name":"_JZq1pWk","InnerNodes":[{"NodeType":"Method","Name":"_WFzMHKi","InnerNodes":[]},{"NodeType":"Method","Name":"ZqyBuL","InnerNodes":[]},{"NodeType":"Method","Name":"_gkpmT6","InnerNodes":[]},{"NodeType":"Method","Name":"_KcEMpAa","InnerNodes":[]},{"NodeType":"Method","Name":"_eM6grS","InnerNodes":[]},{"NodeType":"Method","Name":"_QDkCHN","InnerNodes":[]}]},{"NodeType":"Class","Name":"Au1qsGj","InnerNodes":[{"NodeType":"Method","Name":"_VQ4wfW","InnerNodes":[]},{"NodeType":"Method","Name":"fYmHsa","InnerNodes":[]},{"NodeType":"Method","Name":"Zk6n5Xf","InnerNodes":[]},{"NodeType":"Method","Name":"_QA77Joi","InnerNodes":[]},{"NodeType":"Method","Name":"_QIOFD_","InnerNodes":[]},{"NodeType":"Method","Name":"ejMLpt","InnerNodes":[]}]},{"NodeType":"Class","Name":"_SBoI93x","InnerNodes":[{"NodeType":"Method","Name":"_yLk9gy","InnerNodes":[]}]},{"NodeType":"Class","Name":"Lic2Mpz","InnerNodes":[{"NodeType":"Method","Name":"_DAbDvYw","InnerNodes":[]},{"NodeType":"Method","Name":"BIH0eUp","InnerNodes":[]}]},{"NodeType":"Class","Name":"_DDFFdFV","InnerNodes":[{"NodeType":"Method","Name":"_RmNj9EV","InnerNodes":[]},{"NodeType":"Method","Name":"_QQKSHQa","InnerNodes":[]},{"NodeType":"Method","Name":"cWXWQP","InnerNodes":[]},{"NodeType":"Method","Name":"Nu3bhh","InnerNodes":[]},{"NodeType":"Method","Name":"XG0iLYe","InnerNodes":[]}]},{"NodeType":"Class","Name":"hWQJZD","InnerNodes":[{"NodeType":"Method","Name":"wIUSK0","InnerNodes":[]},{"NodeType":"Method","Name":"_wcBAqB","InnerNodes":[]},{"NodeType":"Method","Name":"snauOO","InnerNodes":[]}]},{"NodeType":"Class","Name":"Ze603uj","InnerNodes":[{"NodeType":"Method","Name":"_Qujgnmg","InnerNodes":[]},{"NodeType":"Method","Name":"ULf6mt","InnerNodes":[]},{"NodeType":"Method","Name":"_IvxjvAU","InnerNodes":[]},{"NodeType":"Method","Name":"rFTz2K","InnerNodes":[]},{"NodeType":"Method","Name":"_QhIkBHG","InnerNodes":[]}]}]}]