[{"NodeType":"Namespace","Name":"_BsgE4Bs","InnerNodes":[{"NodeType":"Class","Name":"e0c9Ov","InnerNodes":[{"NodeType":"Method","Name":"_XZrPZRP","InnerNodes":[]},{"NodeType":"Method","Name":"o_QxKx","InnerNodes":[]},{"NodeType":"Method","Name":"pgZiqe","InnerNodes":[]},{"NodeType":"Method","Name":"_UZCtcaQ","InnerNodes":[]},{"NodeType":"Method","Name":"_egmUFK","InnerNodes":[]},{"NodeType":"Method","Name":"_neS5nh","InnerNodes":[]},{"NodeType":"Method","Name":"_Nb3yqIf","InnerNodes":[]}]},{"NodeType":"Class","Name":"Jt57KpG","InnerNodes":[{"NodeType":"Method","Name":"_pYYPYq","InnerNodes":[]},{"NodeType":"Method","Name":"_Xyq40a","InnerNodes":[]},{"NodeType":"Method","Name":"JRB_Yf1","InnerNodes":[]},{"NodeType":"Method","Name":"QuF8Iy","InnerNodes":[]},{"NodeType":"Method","Name":"_FhTpeQi","InnerNodes":[]},{"NodeType":"Method","Name":"De8tYEn","InnerNodes":[]},{"NodeType":"Method","Name":"_ChEYYhU","InnerNodes":[]}]},{"NodeType":"Class","Name":"_AftJzVh","InnerNodes":[{"NodeType":"Method","Name":"_fHjomp","InnerNodes":[]},{"NodeType":"Method","Name":"_qTg8ir","InnerNodes":[]},{"NodeType":"Method","Name":"_TDijgqX","InnerNodes":[]},{"NodeType":"Method","Name":"_JhUDQH","InnerNodes":[]},{"NodeType":"Method","Name":"_pXTYDC","InnerNodes":[]},{"NodeType":"Method","Name":"_XeCiGZ","InnerNodes":[]}]},{"NodeType":"Class","Name":"xnIZwH","InnerNodes":[{"NodeType":"Method","Name":"OXbzOAY","InnerNodes":[]},{"NodeType":"Method","Name":"kbzTVe","InnerNodes":[]},{"NodeType":"Method","Name":"UKGIutq","InnerNodes":[]}]},{"NodeType":"Class","Name":"_LFEVh31","InnerNodes":[{"NodeType":"Method","Name":"_I3puRy","InnerNodes":[]},{"NodeType":"Method","Name":"Yb8LIPL","InnerNodes":[]},{"NodeType":"Method","Name":"_OMzyAf","InnerNodes":[]},{"NodeType":"Method","Name":"YwciAt","InnerNodes":[]},{"NodeType":"Method","Name":"PRA3dm","InnerNodes":[]},{"NodeType":"Method","Name":"Fffu6j","InnerNodes":[]},{"NodeType":"Method","Name":"_GA6vF4z","InnerNodes":[]}]},{"NodeType":"Class","Name":"_IwWQwE","InnerNodes":[{"NodeType":"Method","Name":"N_wuJX","InnerNodes":[]},{"NodeType":"Method","Name":"_LAKn4mH","InnerNodes":[]},{"NodeType":"Method","Name":"F1Hekx","InnerNodes":[]}]},{"NodeType":"Class","Name":"_Zp9sqfm","InnerNodes":[{"NodeType":"Method","Name":"_WbEG1F","InnerNodes":[]}]},{"NodeType":"Class","Name":"IRgTkRD","InnerNodes":[{"NodeType":"Method","Name":"_ImNsP1","InnerNodes":[]},{"NodeType":"Method","Name":"_RbEAEK1","InnerNodes":[]},{"NodeType":"Method","Name":"PRqnnKe","InnerNodes":[]},{"NodeType":"Method","Name":"_IuyJmE","InnerNodes":[]},{"NodeType":"Method","Name":"YzISraB","InnerNodes":[]},{"NodeType":"Method","Name":"JBTH80n","InnerNodes":[]}]}]},{"NodeType":"Namespace","Name":"tSawRn","InnerNodes":[{"NodeType":"Class","Name":"mmzL7E","InnerNodes":[{"NodeType":"Method","Name":"_EVvYfRF","InnerNodes":[]},{"NodeType":"Method","Name":"i_WuCT","InnerNodes":[]},{"NodeType":"Method","Name":"teUF4t","InnerNodes":[]},{"NodeType":"Method","Name":"FvLQQR","InnerNodes":[]},{"NodeType":"Method","Name":"hIr0Y2","InnerNodes":[]},{"NodeType":"Method","Name":"_IxRd70","InnerNodes":[]},{"NodeType":"Method","Name":"VFbmj70","InnerNodes":[]},{"NodeType":"Method","Name":"vHMDOV","InnerNodes":[]},{"NodeType":"Method","Name":"jbp8wE","InnerNodes":[]}]},{"NodeType":"Class","Name":"_AjGV9QB","InnerNodes":[{"NodeType":"Method","Name":"Ozsb_oI","InnerNodes":[]}]},{"NodeType":"Class","Name":"_Uf3zypd","InnerNodes":[{"NodeType":"Method","Name":"QIHpa4","InnerNodes":[]},{"NodeType":"Method","Name":"eILxi_","InnerNodes":[]},{"NodeType":"Method","Name":"_Mv0DSrF","InnerNodes":[]},{"NodeType":"Method","Name":"_FnIVsic","InnerNodes":[]},{"NodeType":"Method","Name":"He8ySDk","InnerNodes":[]},{"NodeType":"Method","Name":"sywdmN","InnerNodes":[]}]},{"NodeType":"Class","Name":"_LzPXaZ","InnerNodes":[{"NodeType":"Method","Name":"_pcy1VJ","InnerNodes":[]},{"NodeType":"Method","Name":"UOERCn","InnerNodes":[]},{"NodeType":"Method","Name":"_FM8WVKH","InnerNodes":[]},{"NodeType":"Method","Name":"_XvUtsI","InnerNodes":[]},{"NodeType":"Method","Name":"_Ieurdg","InnerNodes":[]}]}]},{"NodeType":"Namespace","Name":"JHAO6i","InnerNodes":[{"NodeType":"Class","Name":"_KfwHYMI","InnerNodes":[{"NodeType":"Method","Name":"zD97tc","InnerNodes":[]},{"NodeType":"Method","Name":"_FIKRuSR","InnerNodes":[]},{"NodeType":"Method","Name":"YXAVTDx","InnerNodes":[]},{"NodeType":"Method","Name":"_EsI2id1","InnerNodes":[]},{"NodeType":"Method","Name":"JCTHhtn","InnerNodes":[]},{"NodeType":"Method","Name":"ZO4rs3B","InnerNodes":[]}]},{"NodeType":"Class","Name":"_Vrdofe8","InnerNodes":[{"NodeType":"Method","Name":"_SarjLnI","InnerNodes":[]},{"NodeType":"Method","Name":"WjEiE_","InnerNodes":[]},{"NodeType":"Method","Name":"_w6UJ45","InnerNodes":[]}]},{"NodeType":"Class","Name":"_DMgfFd","InnerNodes":[{"NodeType":"Method","Name":"GJqMXTq","InnerNodes":[]},{"NodeType":"Method","Name":"EdQa8XN","InnerNodes":[]}]},{"NodeType":"Class","Name":"_OIPbk72","InnerNodes":[{"NodeType":"Method","Name":"iMXgNc","InnerNodes":[]},{"NodeType":"Method","Name":"_gaeJAf","InnerNodes":[]},{"NodeType":"Method","Name":"y2zj8H","InnerNodes":[]},{"NodeType":"Method","Name":"Bk3HS2s","InnerNodes":[]},{"NodeType":"Method","Name":"_hcVHYj","InnerNodes":[]},{"NodeType":"Method","Name":"UV0tAvL","InnerNodes":[]},{"NodeType":"Method","Name":"_IhjXonc","InnerNodes":[]}]}]},{"NodeType":"Namespace","Name":"_AJNuq3","InnerNodes":[{"NodeType":"Class","Name":"_bvYhtL","InnerNodes":[{"NodeType":"Method","Name":"IDxEYXr","InnerNodes":[]}]}]},{"NodeType":"Namespace","Name":"NHCpisI","InnerNodes":[{"NodeType":"Class","Name":"IrFWre","InnerNodes":[{"NodeType":"Method","Name":"RiH2Iq3","InnerNodes":[]},{"NodeType":"Method","Name":"_Q_cpiB","InnerNodes":[]},{"NodeType":"Method","Name":"jbyDjZ","InnerNodes":[]},{"NodeType":"Method","Name":"FbtW9bX","InnerNodes":[]},{"NodeType":"Method","Name":"_F31N1Q","InnerNodes":[]},{"NodeType":"Method","Name":"sdXwHE","InnerNodes":[]},{"NodeType":"Method","Name":"Br1Dtdh","InnerNodes":[]}]},{"NodeType":"Class","Name":"qx_igt","InnerNodes":[{"NodeType":"Method","Name":"HSfNy0V","InnerNodes":[]},{"NodeType":"Method","Name":"_Z0gUnD","InnerNodes":[]},{"NodeType":"Method","Name":"HTkcsg2","InnerNodes":[]}]},{"NodeType":"Class","Name":"_Snvyudh","InnerNodes":[{"NodeType":"Method","Name":"_EWzI8R","InnerNodes":[]},{"NodeType":"Method","Name":"_BXkAtia","InnerNodes":[]},{"NodeType":"Method","Name":"_rQqG9t","InnerNodes":[]},{"NodeType":"Method","Name":"DSZuX4s","InnerNodes":[]}]},{"NodeType":"Class","Name":"ZjDz6o","InnerNodes":[{"NodeType":"Method","Name":"obVvTn","InnerNodes":[]},{"NodeType":"Method","Name":"_m88h0X","InnerNodes":[]}]},{"NodeType":"Class","Name":"FIRZuo1","InnerNodes":[{"NodeType":"Method","Name":"_icmEJU","InnerNodes":[]}]}]},{"NodeType":"Namespace","Name":"_ZRZZotw","InnerNodes":[{"NodeType":"Class","Name":"NWB7rS","InnerNodes":[{"NodeType":"Method","Name":"OKR2IJa","InnerNodes":[]},{"NodeType":"Method","Name":"vc3U56","InnerNodes":[]},{"NodeType":"Method","Name":"_ByJ_ta9","InnerNodes":[]},{"NodeType":"Method","Name":"_CeZoLnu","InnerNodes":[]}]},{"NodeType":"Class","Name":"_HBwde5R","InnerNodes":[{"NodeType":"Method","Name":"_CIItbg","InnerNodes":[]},{"NodeType":"Method","Name":"_ac4TsM","InnerNodes":[]}]},{"NodeType":"Class","Name":"_CeoQ5hj","InnerNodes":[{"NodeType":"Method","Name":"UPIWghe","InnerNodes":[]},{"NodeType":"Method","Name":"KPxi0Tw","InnerNodes":[]},{"NodeType":"Method","Name":"IMwQZtT","InnerNodes":[]},{"NodeType":"Method","Name":"WmrghzD","InnerNodes":[]},{"NodeType":"Method","Name":"Pmr4Dk","InnerNodes":[]},{"NodeType":"Method","Name":"_fAoKV4","InnerNodes":[]},{"NodeType":"Method","Name":"Renz8Sf","InnerNodes":[]},{"NodeType":"Method","Name":"RjwJax6","InnerNodes":[]},{"NodeType":"Method","Name":"QRyThMH","InnerNodes":[]}]},{"NodeType":"Class","Name":"_Kbhmcp","InnerNodes":[{"NodeType":"Method","Name":"ZfjtPe","InnerNodes":[]},{"NodeType":"Method","Name":"BRzGOL","InnerNodes":[]}]},{"NodeType":"Class","Name":"_M0jwvm","InnerNodes":[{"NodeType":"Method","Name":"_KeXGRo9","InnerNodes":[]},{"NodeType":"Method","Name":"nUdCKv","InnerNodes":[]},{"NodeType":"Method","Name":"_p_0JAQ","InnerNodes":[]},{"NodeType":"Method","Name":"_BqqmDpe","InnerNodes":[]}]},{"NodeType":"Class","Name":"FiYw8I","InnerNodes":[{"NodeType":"Method","Name":"_R96eUJ","InnerNodes":[]},{"NodeType":"Method","Name":"SPDBmpY","InnerNodes":[]},{"NodeType":"Method","Name":"LmAZchw","InnerNodes":[]},{"NodeType":"Method","Name":"_I5x6eB","InnerNodes":[]},{"NodeType":"Method","Name":"_YLr3Znt","InnerNodes":[]}]},{"NodeType":"Class","Name":"ZBXvIS0","InnerNodes":[{"NodeType":"Method","Name":"_NGUID6z","InnerNodes":[]},{"NodeType":"Method","Name":"_VaImwJ","InnerNodes":[]},{"NodeType":"Method","Name":"_MX2eJx8","InnerNodes":[]}]},{"NodeType":"Class","Name":"gSHEg3","InnerNodes":[{"NodeType":"Method","Name":"RuZVFLR","InnerNodes":[]},{"NodeType":"Method","Name":"_TL58eX4","InnerNodes":[]},{"NodeType":"Method","Name":"Oy4crU","InnerNodes":[]},{"NodeType":"Method","Name":"_BIQ1TnG","InnerNodes":[]},{"NodeType":"Method","Name":"_SC7jk9","InnerNodes":[]}]}]},{"NodeType":"Namespace","Name":"_bZ6ups","InnerNodes":[{"NodeType":"Class","Name":"_Zv6yJ0m","InnerNodes":[{"NodeType":"Method","Name":"vgr6gi","InnerNodes":[]},{"NodeType":"Method","Name":"_HH27m2q","InnerNodes":[]},{"NodeType":"Method","Name":"JLUA1YN","InnerNodes":[]},{"NodeType":"Method","Name":"xzzLMi","InnerNodes":[]},{"NodeType":"Method","Name":"_Rip9TM","InnerNodes":[]}]}]}]