[{"NodeType":"Namespace","Name":"_FNA2k8","InnerNodes":[{"NodeType":"Class","Name":"kOOTCI","InnerNodes":[{"NodeType":"Method","Name":"Zfv51no","InnerNodes":[]},{"NodeType":"Method","Name":"SE3GIe","InnerNodes":[]},{"NodeType":"Method","Name":"_CtTHSs","InnerNodes":[]}]},{"NodeType":"Class","Name":"_MojUEsL","InnerNodes":[{"NodeType":"Method","Name":"_XcEYJ7","InnerNodes":[]},{"NodeType":"Method","Name":"_NELfIID","InnerNodes":[]},{"NodeType":"Method","Name":"ArIhZI6","InnerNodes":[]}]},{"NodeType":"Class","Name":"M3AxUM","InnerNodes":[{"NodeType":"Method","Name":"zIubDw","InnerNodes":[]},{"NodeType":"Method","Name":"_BP8iK5","InnerNodes":[]},{"NodeType":"Method","Name":"msexsG","InnerNodes":[]},{"NodeType":"Method","Name":"_Dei4vzN","InnerNodes":[]},{"NodeType":"Method","Name":"UemQv04","InnerNodes":[]},{"NodeType":"Method","Name":"_MIO8UI1","InnerNodes":[]},{"NodeType":"Method","Name":"_AVhApXv","InnerNodes":[]}]},{"NodeType":"Class","Name":"_OHmmLs","InnerNodes":[{"NodeType":"Method","Name":"_tj1vSq","InnerNodes":[]},{"NodeType":"Method","Name":"_N5fzQp","InnerNodes":[]},{"NodeType":"Method","Name":"_CocLVW","InnerNodes":[]},{"NodeType":"Method","Name":"FcNUOHI","InnerNodes":[]},{"NodeType":"Method","Name":"EXZP_Wd","InnerNodes":[]},{"NodeType":"Method","Name":"_bSGW4N","InnerNodes":[]},{"NodeType":"Method","Name":"_irijYJ","InnerNodes":[]}]},{"NodeType":"Class","Name":"RrdI2Hk","InnerNodes":[{"NodeType":"Method","Name":"_MazSza","InnerNodes":[]},{"NodeType":"Method","Name":"_BiVTQo","InnerNodes":[]},{"NodeType":"Method","Name":"_Qg6jtd","InnerNodes":[]},{"NodeType":"Method","Name":"_CwreV5M","InnerNodes":[]},{"NodeType":"Method","Name":"S8IiwX","InnerNodes":[]}]}]},{"NodeType":"Namespace","Name":"_cEdGsI","InnerNodes":[{"NodeType":"Class","Name":"UeJuhf","InnerNodes":[{"NodeType":"Method","Name":"_K6zMXD","InnerNodes":[]},{"NodeType":"Method","Name":"_IcBFup9","InnerNodes":[]},{"NodeType":"Method","Name":"C2vdc9","InnerNodes":[]},{"NodeType":"Method","Name":"_Dq2Qway","InnerNodes":[]},{"NodeType":"Method","Name":"_Fzhr2Vd","InnerNodes":[]}]},{"NodeType":"Class","Name":"ZOxXVGR","InnerNodes":[{"NodeType":"Method","Name":"_PvT4dz","InnerNodes":[]},{"NodeType":"Method","Name":"_GXZvIY","InnerNodes":[]}]},{"NodeType":"Class","Name":"_AqiuNcn","InnerNodes":[{"NodeType":"Method","Name":"HwCpzt","InnerNodes":[]},{"NodeType":"Method","Name":"i5dPsy","InnerNodes":[]},{"NodeType":"Method","Name":"LfrbZaH","InnerNodes":[]},{"NodeType":"Method","Name":"LkrZBi","InnerNodes":[]},{"NodeType":"Method","Name":"AHbazO","InnerNodes":[]},{"NodeType":"Method","Name":"hNyeAP","InnerNodes":[]},{"NodeType":"Method","Name":"Xq1itjS","InnerNodes":[]},{"NodeType":"Method","Name":"MmpcZAG","InnerNodes":[]},{"NodeType":"Method","Name":"sHb8W1","InnerNodes":[]}]},{"NodeType":"Class","Name":"_USG9MI","InnerNodes":[{"NodeType":"Method","Name":"Mz9Mum1","InnerNodes":[]}]}]},{"NodeType":"Namespace","Name":"WNpUjBx","InnerNodes":[{"NodeType":"Class","Name":"_BvO9kZ8","InnerNodes":[{"NodeType":"Method","Name":"nTdWbW","InnerNodes":[]},{"NodeType":"Method","Name":"t18XzI","InnerNodes":[]},{"NodeType":"Method","Name":"_FrJTZQF","InnerNodes":[]},{"NodeType":"Method","Name":"ZHeL2Yn","InnerNodes":[]},{"NodeType":"Method","Name":"_wWTuIf","InnerNodes":[]},{"NodeType":"Method","Name":"GEnwjMb","InnerNodes":[]},{"NodeType":"Method","Name":"_vI81_d","InnerNodes":[]},{"NodeType":"Method","Name":"_YmBRyJ3","InnerNodes":[]},{"NodeType":"Method","Name":"cws3wZ","InnerNodes":[]}]},{"NodeType":"Class","Name":"qanuc2","InnerNodes":[{"NodeType":"Method","Name":"QKGP468","InnerNodes":[]}]},{"NodeType":"Class","Name":"_X2GVnc","InnerNodes":[{"NodeType":"Method","Name":"NS6XyNR","InnerNodes":[]},{"NodeType":"Method","Name":"S9Fni4","InnerNodes":[]},{"NodeType":"Method","Name":"OXoZMip","InnerNodes":[]},{"NodeType":"Method","Name":"_oIjKuX","InnerNodes":[]},{"NodeType":"Method","Name":"_dLIcVr","InnerNodes":[]}]},{"NodeType":"Class","Name":"_JB3T85L","InnerNodes":[{"NodeType":"Method","Name":"_DLmT4S_","InnerNodes":[]},{"NodeType":"Method","Name":"_OK8sUIY","InnerNodes":[]},{"NodeType":"Method","Name":"_ivFp5K","InnerNodes":[]},{"NodeType":"Method","Name":"_GiIort","InnerNodes":[]},{"NodeType":"Method","Name":"_WOcCig","InnerNodes":[]}]},{"NodeType":"Class","Name":"_n_Bbku","InnerNodes":[{"NodeType":"Method","Name":"_O9hTXH","InnerNodes":[]},{"NodeType":"Method","Name":"Iw2rLeG","InnerNodes":[]},{"NodeType":"Method","Name":"B9tWhG","InnerNodes":[]},{"NodeType":"Method","Name":"Gi3Jk2V","InnerNodes":[]},{"NodeType":"Method","Name":"KiiwN7i","InnerNodes":[]}]}]},{"NodeType":"Namespace","Name":"_HD39_8G","InnerNodes":[{"NodeType":"Class","Name":"NTG4Z4b","InnerNodes":[{"NodeType":"Method","Name":"sA8kji","InnerNodes":[]},{"NodeType":"Method","Name":"WG5h8I6","InnerNodes":[]},{"NodeType":"Method","Name":"ssc2rv","InnerNodes":[]},{"NodeType":"Method","Name":"_PIIrJBR","InnerNodes":[]},{"NodeType":"Method","Name":"E2Lvvf","InnerNodes":[]}]},{"NodeType":"Class","Name":"ENK9PsM","InnerNodes":[{"NodeType":"Method","Name":"xtsiJz","InnerNodes":[]},{"NodeType":"Method","Name":"_GiASgI","InnerNodes":[]}]}]},{"NodeType":"Namespace","Name":"_RV0mTD4","InnerNodes":[{"NodeType":"Class","Name":"JKgnFW2","InnerNodes":[{"NodeType":"Method","Name":"QXRHdPW","InnerNodes":[]}]},{"NodeType":"Class","Name":"_NFZWa61","InnerNodes":[{"NodeType":"Method","Name":"zohONI","InnerNodes":[]},{"NodeType":"Method","Name":"vAiB8a","InnerNodes":[]}]},{"NodeType":"Class","Name":"_VNiVzZ","InnerNodes":[{"NodeType":"Method","Name":"_tR21mp","InnerNodes":[]},{"NodeType":"Method","Name":"QkhHSXo","InnerNodes":[]},{"NodeType":"Method","Name":"_QsCbmu4","InnerNodes":[]},{"NodeType":"Method","Name":"yuyM46","InnerNodes":[]},{"NodeType":"Method","Name":"QfUCIZt","InnerNodes":[]},{"NodeType":"Method","Name":"_ZcgUyAA","InnerNodes":[]}]}]},{"NodeType":"Namespace","Name":"p4EgKh","InnerNodes":[{"NodeType":"Class","Name":"_WJdAmMA","InnerNodes":[{"NodeType":"Method","Name":"NB6ZWys","InnerNodes":[]},{"NodeType":"Method","Name":"_RwfTIa5","InnerNodes":[]},{"NodeType":"Method","Name":"_BHiCfq","InnerNodes":[]}]},{"NodeType":"Class","Name":"iT9uAr","InnerNodes":[{"NodeType":"Method","Name":"ePBIKc","InnerNodes":[]},{"NodeType":"Method","Name":"_EKY7IHR","InnerNodes":[]},{"NodeType":"Method","Name":"Fsud_Gw","InnerNodes":[]},{"NodeType":"Method","Name":"CcE6vro","InnerNodes":[]},{"NodeType":"Method","Name":"Wue_igp","InnerNodes":[]},{"NodeType":"Method","Name":"_wtpMh9","InnerNodes":[]},{"NodeType":"Method","Name":"_YSWZ2O3","InnerNodes":[]},{"NodeType":"Method","Name":"_OYvYOX","InnerNodes":[]},{"NodeType":"Method","Name":"_HM4U519","InnerNodes":[]}]},{"NodeType":"Class","Name":"EibBfg","InnerNodes":[{"NodeType":"Method","Name":"ATXpY15","InnerNodes":[]},{"NodeType":"Method","Name":"_V4Mbu3","InnerNodes":[]},{"NodeType":"Method","Name":"_cKk5iC","InnerNodes":[]},{"NodeType":"Method","Name":"DtcC1Vg","InnerNodes":[]},{"NodeType":"Method","Name":"_UIjcRyT","InnerNodes":[]},{"NodeType":"Method","Name":"_WStIyJ","InnerNodes":[]},{"NodeType":"Method","Name":"_iRsKRh","InnerNodes":[]}]},{"NodeType":"Class","Name":"DxrIU62","InnerNodes":[{"NodeType":"Method","Name":"_Jo4e6iP","InnerNodes":[]},{"NodeType":"Method","Name":"_ZNSmMG","InnerNodes":[]},{"NodeType":"Method","Name":"F6VoxZ","InnerNodes":[]},{"NodeType":"Method","Name":"ZNfuge","InnerNodes":[]},{"NodeType":"Method","Name":"_KgqLWV","InnerNodes":[]},{"NodeType":"Method","Name":"MA5OaOi","InnerNodes":[]},{"NodeType":"Method","Name":"fXcjm3","InnerNodes":[]},{"NodeType":"Method","Name":"KOiPy4q","InnerNodes":[]},{"NodeType":"Method","Name":"_m6di7F","InnerNodes":[]}]},{"NodeType":"Class","Name":"IkIZHH3","InnerNodes":[{"NodeType":"Method","Name":"TNSIs5r","InnerNodes":[]},{"NodeType":"Method","Name":"_vOXCRO","InnerNodes":[]},{"NodeType":"Method","Name":"_RFFeCQ","InnerNodes":[]},{"NodeType":"Method","Name":"CIqY2W","InnerNodes":[]},{"NodeType":"Method","Name":"_xigatV","InnerNodes":[]},{"NodeType":"Method","Name":"ITEC7a","InnerNodes":[]},{"NodeType":"Method","Name":"_UNWL3Lr","InnerNodes":[]},{"NodeType":"Method","Name":"_YI3A2iM","InnerNodes":[]}]}]},{"NodeType":"Namespace","Name":"Pjm66b","InnerNodes":[{"NodeType":"Class","Name":"UCcUQY","InnerNodes":[{"NodeType":"Method","Name":"eDoKmY","InnerNodes":[]},{"NodeType":"Method","Name":"EDU6hz7","InnerNodes":[]},{"NodeType":"Method","Name":"GAufdq","InnerNodes":[]}]},{"NodeType":"Class","Name":"phX3Bm","InnerNodes":[{"NodeType":"Method","Name":"afgCXM","InnerNodes":[]},{"NodeType":"Method","Name":"_fvnz_t","InnerNodes":[]},{"NodeType":"Method","Name":"_e8oz8U","InnerNodes":[]},{"NodeType":"Method","Name":"_htbW0K","InnerNodes":[]},{"NodeType":"Method","Name":"zvOZ2E","InnerNodes":[]},{"NodeType":"Method","Name":"p8Sb2x","InnerNodes":[]},{"NodeType":"Method","Name":"_JicDpRL","InnerNodes":[]},{"NodeType":"Method","Name":"EWvFAXC","InnerNodes":[]}]},{"NodeType":"Class","Name":"_sxb9fj","InnerNodes":[{"NodeType":"Method","Name":"_nihQEs","InnerNodes":[]},{"NodeType":"Method","Name":"_Kvi77Z","InnerNodes":[]},{"NodeType":"Method","Name":"qpQFsi","InnerNodes":[]},{"NodeType":"Method","Name":"TfEv12Q","InnerNodes":[]},{"NodeType":"Method","Name":"_NBXhr7K","InnerNodes":[]},{"NodeType":"Method","Name":"_YznUs1s","InnerNodes":[]},{"NodeType":"Method","Name":"_SZgEgC","InnerNodes":[]}]},{"NodeType":"Class","Name":"_ZCKvfF","InnerNodes":[{"NodeType":"Method","Name":"K7EGFa","InnerNodes":[]},{"NodeType":"Method","Name":"_MBHzh_g","InnerNodes":[]},{"NodeType":"Method","Name":"_OE0EM2","InnerNodes":[]},{"NodeType":"Method","Name":"_MawNwRW","InnerNodes":[]}]},{"NodeType":"Class","Name":"_euz_mi","InnerNodes":[{"NodeType":"Method","Name":"UONMgiI","InnerNodes":[]},{"NodeType":"Method","Name":"fhMVUI","InnerNodes":[]},{"NodeType":"Method","Name":"xLPJqA","InnerNodes":[]},{"NodeType":"Method","Name":"_YiWRvTv","InnerNodes":[]},{"NodeType":"Method","Name":"HIr8MzG","InnerNodes":[]},{"NodeType":"Method","Name":"HSYH_Pc","InnerNodes":[]},{"NodeType":"Method","Name":"ySBP87","InnerNodes":[]}]}]}]